{
    "Nageur1": {
        "COO": [
            432,
            336
        ],
        "NOM": "Nageur1",
        "TEXTE": "yo",
        "BOUGE": 3,
        "Orientation": 3,
      "TEAM": [
        {
          "N": "18",
          "POKEMON": "Cachamousse",
          "NOM": "Cachamousse",
          "TYPE1": "Tenebre",
          "TYPE2": "Eau",
          "BPV": "84",
          "NIVEAU": 7,
          "SEXE": "m",
          "ATTAQUE1": "Blocage",
          "ATTAQUE2": "Pistolet a O",
          "ATTAQUE3": "Aqua Jet",
          "ATTAQUE4": "Poursuite",
          "PP1": 10,
          "PP2": 25,
          "PP3": 20,
          "PP4": 20,
          "XP": 0,
          "XPMAX": 343,
          "BATK": "69",
          "BDEF": "48",
          "BSPA": "63",
          "BSPD": "51",
          "BSPE": "35",
          "ATK": 16,
          "DEF": 12,
          "SPA": 15,
          "SPD": 15,
          "SPE": 10,
          "PV": 29,
          "PVMAX": 29,
          "OBJET": "",
          "STATUT": "ok",
          "IVATK": 8,
          "IVDEF": 4,
          "IVSPA": 10,
          "IVSPD": 23,
          "IVSPE": 4,
          "IVPV": 4,
          "NATURE": "Foufou",
          "COURBE": "moyenne",
          "EVPV": 0,
          "EVATK": 0,
          "EVDEF": 0,
          "EVSPA": 0,
          "EVSPD": 0,
          "EVSPE": 0,
          "TCAPTURE": "80"
        }
      ],
        "comp": "COMBAT"
    },
    "Nageur2": {
        "COO": [
            336,
            208
        ],
        "NOM": "Nageur2",
        "TEXTE": "yo",
        "BOUGE": 3,
        "Orientation": 0,
      "TEAM": [
        {
          "N": "40",
          "POKEMON": "Martelot",
          "NOM": "Martelot",
          "TYPE1": "Eau",
          "TYPE2": "",
          "BPV": "55",
          "NIVEAU": 10,
          "SEXE": "m",
          "ATTAQUE1": "Ecume",
          "ATTAQUE2": "Danse Pluie",
          "ATTAQUE3": "Aqua Jet",
          "ATTAQUE4": "Morsure",
          "PP1": 25,
          "PP2": 5,
          "PP3": 20,
          "PP4": 25,
          "XP": 0,
          "XPMAX": 1000,
          "BATK": "60",
          "BDEF": "53",
          "BSPA": "45",
          "BSPD": "59",
          "BSPE": "46",
          "ATK": 20,
          "DEF": 17,
          "SPA": 20,
          "SPD": 19,
          "SPE": 19,
          "PV": 32,
          "PVMAX": 32,
          "OBJET": "",
          "STATUT": "ok",
          "IVATK": 13,
          "IVDEF": 9,
          "IVSPA": 29,
          "IVSPD": 10,
          "IVSPE": 23,
          "IVPV": 3,
          "NATURE": "Jovial",
          "COURBE": "moyenne",
          "EVPV": 0,
          "EVATK": 0,
          "EVDEF": 0,
          "EVSPA": 0,
          "EVSPD": 0,
          "EVSPE": 0,
          "TCAPTURE": ""
        }

      ],
        "comp": "COMBAT"
    },
    "Nageuse1": {
        "COO": [
            96,
            208
        ],
        "NOM": "Nageuse1",
        "TEXTE": "yo",
        "BOUGE": 3,
        "Orientation": 0,
      "TEAM": [
        {
          "N": "18",
          "POKEMON": "Cachamousse",
          "NOM": "Cachamousse",
          "TYPE1": "Tenebre",
          "TYPE2": "Eau",
          "BPV": "84",
          "NIVEAU": 13,
          "SEXE": "f",
          "ATTAQUE1": "Blocage",
          "ATTAQUE2": "Pistolet a O",
          "ATTAQUE3": "Aqua Jet",
          "ATTAQUE4": "Poursuite",
          "PP1": 10,
          "PP2": 25,
          "PP3": 20,
          "PP4": 20,
          "XP": 0,
          "XPMAX": 2197,
          "BATK": "69",
          "BDEF": "48",
          "BSPA": "63",
          "BSPD": "51",
          "BSPE": "35",
          "ATK": 23,
          "DEF": 22,
          "SPA": 29,
          "SPD": 19,
          "SPE": 21,
          "PV": 52,
          "PVMAX": 52,
          "OBJET": "",
          "STATUT": "ok",
          "IVATK": 2,
          "IVDEF": 16,
          "IVSPA": 28,
          "IVSPD": 2,
          "IVSPE": 26,
          "IVPV": 26,
          "NATURE": "Relax",
          "COURBE": "moyenne",
          "EVPV": 0,
          "EVATK": 0,
          "EVDEF": 0,
          "EVSPA": 0,
          "EVSPD": 0,
          "EVSPE": 0,
          "TCAPTURE": "80"
        },
        {
          "N": "59",
          "POKEMON": "Cirqua",
          "NOM": "Cirqua",
          "TYPE1": "Eau",
          "TYPE2": "",
          "BPV": "40",
          "NIVEAU": 12,
          "SEXE": "m",
          "ATTAQUE1": "Aqua Jet",
          "ATTAQUE2": "Pistolet a O",
          "ATTAQUE3": "Coup Bas",
          "ATTAQUE4": "Reflet",
          "PP1": 20,
          "PP2": 25,
          "PP3": 5,
          "PP4": 15,
          "XP": 0,
          "XPMAX": 1382,
          "BATK": "51",
          "BDEF": "49",
          "BSPA": "55",
          "BSPD": "55",
          "BSPE": "60",
          "ATK": 24,
          "DEF": 22,
          "SPA": 18,
          "SPD": 23,
          "SPE": 22,
          "PV": 34,
          "PVMAX": 34,
          "OBJET": "",
          "STATUT": "ok",
          "IVATK": 30,
          "IVDEF": 20,
          "IVSPA": 0,
          "IVSPD": 21,
          "IVSPE": 11,
          "IVPV": 9,
          "NATURE": "Lache",
          "COURBE": "rapide",
          "EVPV": 0,
          "EVATK": 0,
          "EVDEF": 0,
          "EVSPA": 0,
          "EVSPD": 0,
          "EVSPE": 0,
          "TCAPTURE": ""
        }

      ],
        "comp": "COMBAT"
    }
}